civiscompute/__init__.py
civiscompute/caching.py
civiscompute/cancel.py
civiscompute/cli.py
civiscompute/defaults.py
civiscompute/get.py
civiscompute/notebooks.py
civiscompute/parsing.py
civiscompute/stat.py
civiscompute/sub.py
civiscompute/utils.py
civiscompute/version.py
civiscompute/tests/__init__.py
civiscompute/tests/conftest.py
civiscompute/tests/test_aws_creds.py
civiscompute/tests/test_caching.py
civiscompute/tests/test_cancel.py
civiscompute/tests/test_get.py
civiscompute/tests/test_notebooks.py
civiscompute/tests/test_parsing.py
civiscompute/tests/test_stat.py
civiscompute/tests/test_sub.py
civiscompute/tests/test_utils.py
civis_compute-0.2.0.dist-info/LICENSE.txt
civis_compute-0.2.0.dist-info/METADATA
civis_compute-0.2.0.dist-info/WHEEL
civis_compute-0.2.0.dist-info/entry_points.txt
civis_compute-0.2.0.dist-info/top_level.txt
civis_compute-0.2.0.dist-info/RECORD
