Metadata-Version: 2.1
Name: civis-compute
Version: 0.2.0
Summary: Batch computing in the cloud with Civis Platform.
Home-page: https://www.civisanalytics.com
Author: Civis Analytics Inc
Author-email: opensource@civisanalytics.com
License: BSD-3
Platform: UNKNOWN
Requires-Dist: click (~=6.7)
Requires-Dist: nbformat (~=4.4)
Requires-Dist: nbconvert (~=5.3)
Requires-Dist: civis (~=1.6)
Requires-Dist: pyyaml (>=5.1)
Requires-Dist: python-dateutil (~=2.6)
Requires-Dist: ipython (~=5.4) ; python_version >= "2.7" and python_version < "3.0"
Requires-Dist: ipython (~=6.2) ; python_version >= "3.0"
